{
  "id": "E2023008",
  "prefix": "Glencoe XI",
  "names": ["Back To Schoolish"],
  "startDate": "10th of February",
  "endDate": "11th of February",
  "features": {
    "accommodation": ["Glencoe Youth Hostel"]
  },
  "description": "Third time lucky maybe? I took to the Glencoe shared room for the first time with hopes of finally getting those two Munros that had defeated me twice. Had a good fuel-up with salmon and big-heap-veggies, and a very strange conversation with some hostel weapons, and got a classic supreme hostel sleep in. Well, only to be woken up by some old dude thanking me for not waking him up when I came to bed?!?! Okay, cool. Anyway, I actually wimped out this time and took the alternative ridge to the schoolhouse. Yeah, no scrambling. I wanted those Munros. It tunred out to be worth it, they're a good burn and I met a good hill companion who had some fine reccies for the upcoming Wrocław trip. And sorry Mark, but the walk-out is not the most beautiful in Scotland. It's just a bog slog.",
  "images": [
    {
      "url": "https://lewisbritton.com/images/blog/instant-gram/2023/glencoe-xi/1.jpg",
      "alt": "glencoe-xi-1"
    },
    {
      "url": "https://lewisbritton.com/images/blog/instant-gram/2023/glencoe-xi/2.jpg",
      "alt": "glencoe-xi-2"
    },
    {
      "url": "https://lewisbritton.com/images/blog/instant-gram/2023/glencoe-xi/3.jpg",
      "alt": "glencoe-xi-3"
    },
    {
      "url": "https://lewisbritton.com/images/blog/instant-gram/2023/glencoe-xi/4.jpg",
      "alt": "glencoe-xi-4"
    },
    {
      "url": "https://lewisbritton.com/images/blog/instant-gram/2023/glencoe-xi/5.jpg",
      "alt": "glencoe-xi-5"
    },
    {
      "url": "https://lewisbritton.com/images/blog/instant-gram/2023/glencoe-xi/6.jpg",
      "alt": "glencoe-xi-6"
    },
    {
      "url": "https://lewisbritton.com/images/blog/instant-gram/2023/glencoe-xi/7.jpg",
      "alt": "glencoe-xi-7"
    },
    {
      "url": "https://lewisbritton.com/images/blog/instant-gram/2023/glencoe-xi/8.jpg",
      "alt": "glencoe-xi-8"
    },
    {
      "url": "https://lewisbritton.com/images/blog/instant-gram/2023/glencoe-xi/9.jpg",
      "alt": "glencoe-xi-9"
    },
    {
      "url": "https://lewisbritton.com/images/blog/instant-gram/2023/glencoe-xi/10.jpg",
      "alt": "glencoe-xi-10"
    },
    {
      "url": "https://lewisbritton.com/images/blog/instant-gram/2023/glencoe-xi/11.jpg",
      "alt": "glencoe-xi-11"
    },
    {
      "url": "https://lewisbritton.com/images/blog/instant-gram/2023/glencoe-xi/12.jpg",
      "alt": "glencoe-xi-12"
    }
  ]
}
