{
  "id": "E2024005",
  "names": ["Sewing The Law"],
  "startDate": "3rd of February",
  "description": "With the poor forecast north continuing, it was finally time to take to England again. Well, basically. Their efforts to name each individual mound top down't' there in't' Borders is admirable. I am quite sad we didn't get to bag White Cleuch and Black Rig. Anyway, started off pretty windy but ended up being a decent proj. Not too much rain, mostly sunshine. It was also a very unexpected five-thousand feet day. Will never forget the legend on Beinn Donald One having to backtrack a fence to get cairn: sticks. Admirable. Tried for a coffee in Moffat afterwards but too late. Made up for it in the evening though with the first desk wasted of the year; some Double Disco's and Erdies. Ha, and three-quarter-bottle-rum.",
  "images": [
    {
      "url": "https://lewisbritton.com/images/blog/instant-gram/2024/sewing-the-law/1.jpg",
      "alt": "sewing-the-law-1"
    },
    {
      "url": "https://lewisbritton.com/images/blog/instant-gram/2024/sewing-the-law/2.jpg",
      "alt": "sewing-the-law-2"
    },
    {
      "url": "https://lewisbritton.com/images/blog/instant-gram/2024/sewing-the-law/3.jpg",
      "alt": "sewing-the-law-3"
    },
    {
      "url": "https://lewisbritton.com/images/blog/instant-gram/2024/sewing-the-law/4.jpg",
      "alt": "sewing-the-law-4"
    },
    {
      "url": "https://lewisbritton.com/images/blog/instant-gram/2024/sewing-the-law/5.jpg",
      "alt": "sewing-the-law-5"
    },
    {
      "url": "https://lewisbritton.com/images/blog/instant-gram/2024/sewing-the-law/6.jpg",
      "alt": "sewing-the-law-6"
    },
    {
      "url": "https://lewisbritton.com/images/blog/instant-gram/2024/sewing-the-law/7.jpg",
      "alt": "sewing-the-law-7"
    },
    {
      "url": "https://lewisbritton.com/images/blog/instant-gram/2024/sewing-the-law/8.jpg",
      "alt": "sewing-the-law-8"
    },
    {
      "url": "https://lewisbritton.com/images/blog/instant-gram/2024/sewing-the-law/9.jpg",
      "alt": "sewing-the-law-9"
    },
    {
      "url": "https://lewisbritton.com/images/blog/instant-gram/2024/sewing-the-law/10.jpg",
      "alt": "sewing-the-law-10"
    },
    {
      "url": "https://lewisbritton.com/images/blog/instant-gram/2024/sewing-the-law/11.jpg",
      "alt": "sewing-the-law-11"
    }
  ]
}
