{
  "countries": [],
  "cities": [],
  "airports": [],
  "accommodation": [],
  "districts": [],
  "attractions": [],
  "parks": [],
  "food": [],
  "drink": [],
  "restaurants": [],
  "bars": [],
  "cafes": [],
  "bakeries": [],
  "chocolatiers": [],
  "gelaterias": [],
  "markets": [],
  "supermarkets": [],
  "departmentStores": [],
  "clothingStores": [],
  "interiorDesignStores": [],
  "technologyStores": [],
  "audioStores": [],
  "kitchenStores": [],
  "stationeryStores": [],
  "bookStores": [],
  "japaneseStores": [],
  "bicycleStores": [],
  "outdoorStores": [],
  "tennisStores": [],
  "uniqueElements": [],
  "nostalgiaEffect": []
}
